erroranalyzer/__init__.py
erroranalyzer/erroranalyzer.py
erroranalyzer/libea.so
erroranalyzer-2.2.1.dist-info/LICENSE
erroranalyzer-2.2.1.dist-info/METADATA
erroranalyzer-2.2.1.dist-info/WHEEL
erroranalyzer-2.2.1.dist-info/top_level.txt
erroranalyzer-2.2.1.dist-info/RECORD
