Metadata-Version: 2.1
Name: erroranalyzer
Version: 2.2.1
Summary: ErrorAnalyzer is the EDA tool of choice to understand and find simulation failures faster
Home-page: https://github.com/semify-eda/go.debug
Author: semify
Author-email: office@semify-eda.com
License: UNKNOWN
Project-URL: Website, https://www.semify-eda.com
Platform: UNKNOWN
Classifier: Programming Language :: Python :: 3
Classifier: License :: Other/Proprietary License
Classifier: Operating System :: POSIX :: Linux
Requires-Python: >=3.6
License-File: LICENSE
